{
	"graph_name": "TryAutoStartPuzzleForCurrentContext",
	"graph_type": "Function",
	"entry_node_id": "K2Node_FunctionEntry_0",
	"has_latent_nodes": false,
	"has_error_nodes": true,
	"has_warning_nodes": false,
	"locals": [],
	"returns": [
		"bStartedPuzzle (Boolean)",
		"bStartedPuzzle (Boolean)",
		"bStartedPuzzle (Boolean)",
		"bStartedPuzzle (Boolean)",
		"bStartedPuzzle (Boolean)",
		"bStartedPuzzle (Boolean)"
	],
	"summary":
	{
		"purpose": "Starts a flow, state transition, or activation sequence.",
		"reads_variables": [
			"bAutoStartFirstPuzzleForCurrentGhost",
			"bPuzzleRestoredFromSave",
			"bHasActivePuzzle",
			"CurrentGhostId"
		],
		"writes_variables": [],
		"calls": [
			"Debug Info",
			"Get Sender Name",
			"Start Next Valid Puzzle for Current Context"
		],
		"called_by": [
			"HandleGhostChanged",
			"HandleWorldModeChanged"
		],
		"branch_points": [
			"Branch"
		]
	},
	"nodes": [
		{
			"node_id": "K2Node_FunctionEntry_0",
			"node_name": "K2Node_FunctionEntry_0",
			"node_kind": "FunctionEntry",
			"ue_class": "K2Node_FunctionEntry",
			"title": "TryAutoStartPuzzleForCurrentContext",
			"title_single_line": "TryAutoStartPuzzleForCurrentContext",
			"comment": "",
			"guid": "fe88e4e7-4f1f-f6ce-8c55-fc97296604cd",
			"x": -720,
			"y": 0,
			"has_error": false,
			"has_warning": false,
			"pins": [
				{
					"pin_name": "then",
					"direction": "Output",
					"category": "exec",
					"subcategory": "None",
					"resolved_type": "exec",
					"default_value": "",
					"linked_count": 1
				}
			],
			"target_class": "TryAutoStartPuzzleForCurrentContext"
		},
		{
			"node_id": "K2Node_FunctionResult_2",
			"node_name": "K2Node_FunctionResult_2",
			"node_kind": "Return",
			"ue_class": "K2Node_FunctionResult",
			"title": "Return Node",
			"title_single_line": "Return Node",
			"comment": "",
			"guid": "f4381c49-4ad8-0173-17ec-dbb972330811",
			"x": 112,
			"y": 432,
			"has_error": false,
			"has_warning": false,
			"pins": [
				{
					"pin_name": "execute",
					"direction": "Input",
					"category": "exec",
					"subcategory": "None",
					"resolved_type": "exec",
					"default_value": "",
					"linked_count": 1
				},
				{
					"pin_name": "bStartedPuzzle",
					"direction": "Input",
					"category": "bool",
					"subcategory": "None",
					"resolved_type": "Boolean",
					"default_value": "false",
					"linked_count": 0
				}
			],
			"target_class": "TryAutoStartPuzzleForCurrentContext"
		},
		{
			"node_id": "K2Node_VariableGet_0",
			"node_name": "K2Node_VariableGet_0",
			"node_kind": "VariableGet",
			"ue_class": "K2Node_VariableGet",
			"title": "Get bAutoStartFirstPuzzleForCurrentGhost",
			"title_single_line": "Get bAutoStartFirstPuzzleForCurrentGhost",
			"comment": "",
			"guid": "675d8bad-4a2a-b9aa-92fc-9f957180e1fb",
			"x": -624,
			"y": 160,
			"has_error": false,
			"has_warning": false,
			"pins": [
				{
					"pin_name": "bAutoStartFirstPuzzleForCurrentGhost",
					"direction": "Output",
					"category": "bool",
					"subcategory": "None",
					"resolved_type": "Boolean",
					"default_value": "false",
					"linked_count": 1
				},
				{
					"pin_name": "self",
					"direction": "Input",
					"category": "object",
					"subcategory": "None",
					"resolved_type": "BP_PuzzleController_C",
					"default_value": "",
					"linked_count": 0
				}
			],
			"target_class": "TryAutoStartPuzzleForCurrentContext"
		},
		{
			"node_id": "K2Node_IfThenElse_0",
			"node_name": "K2Node_IfThenElse_0",
			"node_kind": "Branch",
			"ue_class": "K2Node_IfThenElse",
			"title": "Branch",
			"title_single_line": "Branch",
			"comment": "",
			"guid": "74ae2293-4251-e9ea-d7c2-7991cb6e7bd5",
			"x": -192,
			"y": 0,
			"has_error": false,
			"has_warning": false,
			"pins": [
				{
					"pin_name": "execute",
					"direction": "Input",
					"category": "exec",
					"subcategory": "None",
					"resolved_type": "exec",
					"default_value": "",
					"linked_count": 1
				},
				{
					"pin_name": "Condition",
					"direction": "Input",
					"category": "bool",
					"subcategory": "None",
					"resolved_type": "Boolean",
					"default_value": "true",
					"linked_count": 1
				},
				{
					"pin_name": "then",
					"direction": "Output",
					"category": "exec",
					"subcategory": "None",
					"resolved_type": "exec",
					"default_value": "",
					"linked_count": 1
				},
				{
					"pin_name": "else",
					"direction": "Output",
					"category": "exec",
					"subcategory": "None",
					"resolved_type": "exec",
					"default_value": "",
					"linked_count": 1
				}
			],
			"target_class": "TryAutoStartPuzzleForCurrentContext"
		},
		{
			"node_id": "K2Node_FunctionResult_0",
			"node_name": "K2Node_FunctionResult_0",
			"node_kind": "Return",
			"ue_class": "K2Node_FunctionResult",
			"title": "Return Node",
			"title_single_line": "Return Node",
			"comment": "",
			"guid": "df70f901-4d69-1f33-b7c9-c09ad06743ce",
			"x": 1104,
			"y": 416,
			"has_error": false,
			"has_warning": false,
			"pins": [
				{
					"pin_name": "execute",
					"direction": "Input",
					"category": "exec",
					"subcategory": "None",
					"resolved_type": "exec",
					"default_value": "",
					"linked_count": 0
				},
				{
					"pin_name": "bStartedPuzzle",
					"direction": "Input",
					"category": "bool",
					"subcategory": "None",
					"resolved_type": "Boolean",
					"default_value": "true",
					"linked_count": 0
				}
			],
			"target_class": "TryAutoStartPuzzleForCurrentContext"
		},
		{
			"node_id": "K2Node_VariableGet_1",
			"node_name": "K2Node_VariableGet_1",
			"node_kind": "VariableGet",
			"ue_class": "K2Node_VariableGet",
			"title": "Get bPuzzleRestoredFromSave",
			"title_single_line": "Get bPuzzleRestoredFromSave",
			"comment": "",
			"guid": "97b50a3e-4ff2-eed3-2404-dca5bcbbd5fa",
			"x": -176,
			"y": -112,
			"has_error": false,
			"has_warning": false,
			"pins": [
				{
					"pin_name": "bPuzzleRestoredFromSave",
					"direction": "Output",
					"category": "bool",
					"subcategory": "None",
					"resolved_type": "Boolean",
					"default_value": "false",
					"linked_count": 1
				},
				{
					"pin_name": "self",
					"direction": "Input",
					"category": "object",
					"subcategory": "None",
					"resolved_type": "BP_PuzzleController_C",
					"default_value": "",
					"linked_count": 0
				}
			],
			"target_class": "TryAutoStartPuzzleForCurrentContext"
		},
		{
			"node_id": "K2Node_IfThenElse_1",
			"node_name": "K2Node_IfThenElse_1",
			"node_kind": "Branch",
			"ue_class": "K2Node_IfThenElse",
			"title": "Branch",
			"title_single_line": "Branch",
			"comment": "",
			"guid": "e5008c57-488d-2fdd-3ef9-8ca23f33933b",
			"x": 192,
			"y": 0,
			"has_error": false,
			"has_warning": false,
			"pins": [
				{
					"pin_name": "execute",
					"direction": "Input",
					"category": "exec",
					"subcategory": "None",
					"resolved_type": "exec",
					"default_value": "",
					"linked_count": 1
				},
				{
					"pin_name": "Condition",
					"direction": "Input",
					"category": "bool",
					"subcategory": "None",
					"resolved_type": "Boolean",
					"default_value": "true",
					"linked_count": 1
				},
				{
					"pin_name": "then",
					"direction": "Output",
					"category": "exec",
					"subcategory": "None",
					"resolved_type": "exec",
					"default_value": "",
					"linked_count": 1
				},
				{
					"pin_name": "else",
					"direction": "Output",
					"category": "exec",
					"subcategory": "None",
					"resolved_type": "exec",
					"default_value": "",
					"linked_count": 1
				}
			],
			"target_class": "TryAutoStartPuzzleForCurrentContext"
		},
		{
			"node_id": "K2Node_CallFunction_2",
			"node_name": "K2Node_CallFunction_2",
			"node_kind": "FunctionCall",
			"ue_class": "K2Node_CallFunction",
			"title": "Debug Info",
			"title_single_line": "Debug Info",
			"comment": "",
			"guid": "b3c21038-4bae-81f9-1c67-e1a6e1188e66",
			"x": 592,
			"y": -336,
			"has_error": false,
			"has_warning": false,
			"pins": [
				{
					"pin_name": "execute",
					"direction": "Input",
					"category": "exec",
					"subcategory": "None",
					"resolved_type": "exec",
					"default_value": "",
					"linked_count": 1
				},
				{
					"pin_name": "then",
					"direction": "Output",
					"category": "exec",
					"subcategory": "None",
					"resolved_type": "exec",
					"default_value": "",
					"linked_count": 1
				},
				{
					"pin_name": "self",
					"direction": "Input",
					"category": "object",
					"subcategory": "None",
					"resolved_type": "BFL_Debug_C",
					"default_value": "",
					"linked_count": 0
				},
				{
					"pin_name": "WorldContextObject",
					"direction": "Input",
					"category": "object",
					"subcategory": "None",
					"resolved_type": "Object",
					"default_value": "",
					"linked_count": 1
				},
				{
					"pin_name": "Category",
					"direction": "Input",
					"category": "byte",
					"subcategory": "None",
					"resolved_type": "Byte/Enum",
					"default_value": "NewEnumerator2",
					"linked_count": 0
				},
				{
					"pin_name": "SenderName",
					"direction": "Input",
					"category": "name",
					"subcategory": "None",
					"resolved_type": "Name",
					"default_value": "None",
					"linked_count": 1
				},
				{
					"pin_name": "Message",
					"direction": "Input",
					"category": "string",
					"subcategory": "None",
					"resolved_type": "String",
					"default_value": "[PuzzleController] Auto-start skipped because puzzle state was restored from save",
					"linked_count": 0
				},
				{
					"pin_name": "__WorldContext",
					"direction": "Input",
					"category": "object",
					"subcategory": "None",
					"resolved_type": "Object",
					"default_value": "",
					"linked_count": 0
				}
			],
			"target_class": "TryAutoStartPuzzleForCurrentContext"
		},
		{
			"node_id": "K2Node_Self_1",
			"node_name": "K2Node_Self_1",
			"node_kind": "SelfReference",
			"ue_class": "K2Node_Self",
			"title": "Self-Reference",
			"title_single_line": "Self-Reference",
			"comment": "",
			"guid": "01c0f4db-4564-3ab3-60af-b2b7735aa596",
			"x": 224,
			"y": -256,
			"has_error": false,
			"has_warning": false,
			"pins": [
				{
					"pin_name": "self",
					"direction": "Output",
					"category": "object",
					"subcategory": "self",
					"resolved_type": "object",
					"default_value": "",
					"linked_count": 2
				}
			],
			"target_class": "TryAutoStartPuzzleForCurrentContext"
		},
		{
			"node_id": "K2Node_CallFunction_3",
			"node_name": "K2Node_CallFunction_3",
			"node_kind": "FunctionCall",
			"ue_class": "K2Node_CallFunction",
			"title": "Get Sender Name",
			"title_single_line": "Get Sender Name",
			"comment": "",
			"guid": "422e3b27-421b-5460-11e1-c096878b0b28",
			"x": 384,
			"y": -208,
			"has_error": false,
			"has_warning": false,
			"pins": [
				{
					"pin_name": "self",
					"direction": "Input",
					"category": "object",
					"subcategory": "None",
					"resolved_type": "BFL_Debug_C",
					"default_value": "",
					"linked_count": 0
				},
				{
					"pin_name": "Ref",
					"direction": "Input",
					"category": "object",
					"subcategory": "None",
					"resolved_type": "Object",
					"default_value": "",
					"linked_count": 1
				},
				{
					"pin_name": "__WorldContext",
					"direction": "Input",
					"category": "object",
					"subcategory": "None",
					"resolved_type": "Object",
					"default_value": "",
					"linked_count": 0
				},
				{
					"pin_name": "Name",
					"direction": "Output",
					"category": "name",
					"subcategory": "None",
					"resolved_type": "Name",
					"default_value": "None",
					"linked_count": 1
				}
			],
			"target_class": "TryAutoStartPuzzleForCurrentContext"
		},
		{
			"node_id": "K2Node_FunctionResult_3",
			"node_name": "K2Node_FunctionResult_3",
			"node_kind": "Return",
			"ue_class": "K2Node_FunctionResult",
			"title": "Return Node",
			"title_single_line": "Return Node",
			"comment": "",
			"guid": "66d2d7d4-47f2-659a-fe6c-f7adc94a10ed",
			"x": 1280,
			"y": -336,
			"has_error": false,
			"has_warning": false,
			"pins": [
				{
					"pin_name": "execute",
					"direction": "Input",
					"category": "exec",
					"subcategory": "None",
					"resolved_type": "exec",
					"default_value": "",
					"linked_count": 1
				},
				{
					"pin_name": "bStartedPuzzle",
					"direction": "Input",
					"category": "bool",
					"subcategory": "None",
					"resolved_type": "Boolean",
					"default_value": "false",
					"linked_count": 0
				}
			],
			"target_class": "TryAutoStartPuzzleForCurrentContext"
		},
		{
			"node_id": "K2Node_VariableGet_2",
			"node_name": "K2Node_VariableGet_2",
			"node_kind": "VariableGet",
			"ue_class": "K2Node_VariableGet",
			"title": "Get bHasActivePuzzle",
			"title_single_line": "Get bHasActivePuzzle",
			"comment": "",
			"guid": "84ee1ead-4833-cdd6-f2ef-dc854c0f13c2",
			"x": 368,
			"y": 160,
			"has_error": false,
			"has_warning": false,
			"pins": [
				{
					"pin_name": "bHasActivePuzzle",
					"direction": "Output",
					"category": "bool",
					"subcategory": "None",
					"resolved_type": "Boolean",
					"default_value": "false",
					"linked_count": 1
				},
				{
					"pin_name": "self",
					"direction": "Input",
					"category": "object",
					"subcategory": "None",
					"resolved_type": "BP_PuzzleController_C",
					"default_value": "",
					"linked_count": 0
				}
			],
			"target_class": "TryAutoStartPuzzleForCurrentContext"
		},
		{
			"node_id": "K2Node_IfThenElse_2",
			"node_name": "K2Node_IfThenElse_2",
			"node_kind": "Branch",
			"ue_class": "K2Node_IfThenElse",
			"title": "Branch",
			"title_single_line": "Branch",
			"comment": "",
			"guid": "68259820-4eb1-eeb9-10f2-2cb8877c6b4d",
			"x": 640,
			"y": 32,
			"has_error": false,
			"has_warning": false,
			"pins": [
				{
					"pin_name": "execute",
					"direction": "Input",
					"category": "exec",
					"subcategory": "None",
					"resolved_type": "exec",
					"default_value": "",
					"linked_count": 1
				},
				{
					"pin_name": "Condition",
					"direction": "Input",
					"category": "bool",
					"subcategory": "None",
					"resolved_type": "Boolean",
					"default_value": "true",
					"linked_count": 1
				},
				{
					"pin_name": "then",
					"direction": "Output",
					"category": "exec",
					"subcategory": "None",
					"resolved_type": "exec",
					"default_value": "",
					"linked_count": 1
				},
				{
					"pin_name": "else",
					"direction": "Output",
					"category": "exec",
					"subcategory": "None",
					"resolved_type": "exec",
					"default_value": "",
					"linked_count": 1
				}
			],
			"target_class": "TryAutoStartPuzzleForCurrentContext"
		},
		{
			"node_id": "K2Node_CallFunction_4",
			"node_name": "K2Node_CallFunction_4",
			"node_kind": "FunctionCall",
			"ue_class": "K2Node_CallFunction",
			"title": "Debug Info",
			"title_single_line": "Debug Info",
			"comment": "",
			"guid": "fd023fba-4fc4-0726-5a7a-deb3803a3a50",
			"x": 1504,
			"y": -112,
			"has_error": false,
			"has_warning": false,
			"pins": [
				{
					"pin_name": "execute",
					"direction": "Input",
					"category": "exec",
					"subcategory": "None",
					"resolved_type": "exec",
					"default_value": "",
					"linked_count": 1
				},
				{
					"pin_name": "then",
					"direction": "Output",
					"category": "exec",
					"subcategory": "None",
					"resolved_type": "exec",
					"default_value": "",
					"linked_count": 1
				},
				{
					"pin_name": "self",
					"direction": "Input",
					"category": "object",
					"subcategory": "None",
					"resolved_type": "BFL_Debug_C",
					"default_value": "",
					"linked_count": 0
				},
				{
					"pin_name": "WorldContextObject",
					"direction": "Input",
					"category": "object",
					"subcategory": "None",
					"resolved_type": "Object",
					"default_value": "",
					"linked_count": 1
				},
				{
					"pin_name": "Category",
					"direction": "Input",
					"category": "byte",
					"subcategory": "None",
					"resolved_type": "Byte/Enum",
					"default_value": "NewEnumerator2",
					"linked_count": 0
				},
				{
					"pin_name": "SenderName",
					"direction": "Input",
					"category": "name",
					"subcategory": "None",
					"resolved_type": "Name",
					"default_value": "None",
					"linked_count": 1
				},
				{
					"pin_name": "Message",
					"direction": "Input",
					"category": "string",
					"subcategory": "None",
					"resolved_type": "String",
					"default_value": "[PuzzleController] Auto-start skipped because an active puzzle already exists",
					"linked_count": 0
				},
				{
					"pin_name": "__WorldContext",
					"direction": "Input",
					"category": "object",
					"subcategory": "None",
					"resolved_type": "Object",
					"default_value": "",
					"linked_count": 0
				}
			],
			"target_class": "TryAutoStartPuzzleForCurrentContext"
		},
		{
			"node_id": "K2Node_Self_2",
			"node_name": "K2Node_Self_2",
			"node_kind": "SelfReference",
			"ue_class": "K2Node_Self",
			"title": "Self-Reference",
			"title_single_line": "Self-Reference",
			"comment": "",
			"guid": "264e3c7e-4721-4e01-38bd-68bde5b3af62",
			"x": 1136,
			"y": -32,
			"has_error": false,
			"has_warning": false,
			"pins": [
				{
					"pin_name": "self",
					"direction": "Output",
					"category": "object",
					"subcategory": "self",
					"resolved_type": "object",
					"default_value": "",
					"linked_count": 2
				}
			],
			"target_class": "TryAutoStartPuzzleForCurrentContext"
		},
		{
			"node_id": "K2Node_CallFunction_5",
			"node_name": "K2Node_CallFunction_5",
			"node_kind": "FunctionCall",
			"ue_class": "K2Node_CallFunction",
			"title": "Get Sender Name",
			"title_single_line": "Get Sender Name",
			"comment": "",
			"guid": "cf4833af-4244-1946-04a1-089f4d58975b",
			"x": 1296,
			"y": 16,
			"has_error": false,
			"has_warning": false,
			"pins": [
				{
					"pin_name": "self",
					"direction": "Input",
					"category": "object",
					"subcategory": "None",
					"resolved_type": "BFL_Debug_C",
					"default_value": "",
					"linked_count": 0
				},
				{
					"pin_name": "Ref",
					"direction": "Input",
					"category": "object",
					"subcategory": "None",
					"resolved_type": "Object",
					"default_value": "",
					"linked_count": 1
				},
				{
					"pin_name": "__WorldContext",
					"direction": "Input",
					"category": "object",
					"subcategory": "None",
					"resolved_type": "Object",
					"default_value": "",
					"linked_count": 0
				},
				{
					"pin_name": "Name",
					"direction": "Output",
					"category": "name",
					"subcategory": "None",
					"resolved_type": "Name",
					"default_value": "None",
					"linked_count": 1
				}
			],
			"target_class": "TryAutoStartPuzzleForCurrentContext"
		},
		{
			"node_id": "K2Node_FunctionResult_4",
			"node_name": "K2Node_FunctionResult_4",
			"node_kind": "Return",
			"ue_class": "K2Node_FunctionResult",
			"title": "Return Node",
			"title_single_line": "Return Node",
			"comment": "",
			"guid": "dcefc3f3-4922-f525-e4b2-0d89387f9bdf",
			"x": 2192,
			"y": -112,
			"has_error": false,
			"has_warning": false,
			"pins": [
				{
					"pin_name": "execute",
					"direction": "Input",
					"category": "exec",
					"subcategory": "None",
					"resolved_type": "exec",
					"default_value": "",
					"linked_count": 1
				},
				{
					"pin_name": "bStartedPuzzle",
					"direction": "Input",
					"category": "bool",
					"subcategory": "None",
					"resolved_type": "Boolean",
					"default_value": "false",
					"linked_count": 0
				}
			],
			"target_class": "TryAutoStartPuzzleForCurrentContext"
		},
		{
			"node_id": "K2Node_Knot_0",
			"node_name": "K2Node_Knot_0",
			"node_kind": "Reroute",
			"ue_class": "K2Node_Knot",
			"title": "Reroute Node",
			"title_single_line": "Reroute Node",
			"comment": "",
			"guid": "b409a62e-4d6a-b22c-c727-a39f8eda706b",
			"x": 1072,
			"y": -80,
			"has_error": false,
			"has_warning": false,
			"pins": [
				{
					"pin_name": "InputPin",
					"direction": "Input",
					"category": "exec",
					"subcategory": "None",
					"resolved_type": "exec",
					"default_value": "",
					"linked_count": 1
				},
				{
					"pin_name": "OutputPin",
					"direction": "Output",
					"category": "exec",
					"subcategory": "None",
					"resolved_type": "exec",
					"default_value": "",
					"linked_count": 1
				}
			],
			"target_class": "TryAutoStartPuzzleForCurrentContext"
		},
		{
			"node_id": "K2Node_VariableGet_3",
			"node_name": "K2Node_VariableGet_3",
			"node_kind": "VariableGet",
			"ue_class": "K2Node_VariableGet",
			"title": "Get CurrentGhostId",
			"title_single_line": "Get CurrentGhostId",
			"comment": "",
			"guid": "3e4ce30e-4cd9-b464-dff3-388111d7af7f",
			"x": 592,
			"y": 224,
			"has_error": false,
			"has_warning": false,
			"pins": [
				{
					"pin_name": "CurrentGhostId",
					"direction": "Output",
					"category": "name",
					"subcategory": "None",
					"resolved_type": "Name",
					"default_value": "None",
					"linked_count": 1
				},
				{
					"pin_name": "self",
					"direction": "Input",
					"category": "object",
					"subcategory": "None",
					"resolved_type": "BP_PuzzleController_C",
					"default_value": "",
					"linked_count": 0
				}
			],
			"target_class": "TryAutoStartPuzzleForCurrentContext"
		},
		{
			"node_id": "K2Node_PromotableOperator_0",
			"node_name": "K2Node_PromotableOperator_0",
			"node_kind": "Unknown",
			"ue_class": "K2Node_PromotableOperator",
			"title": "Not Equal (Name)",
			"title_single_line": "Not Equal (Name)",
			"comment": "",
			"guid": "4e36bbb8-4b16-2650-07b9-8886e46197bc",
			"x": 800,
			"y": 304,
			"has_error": false,
			"has_warning": false,
			"pins": [
				{
					"pin_name": "A",
					"direction": "Input",
					"category": "name",
					"subcategory": "None",
					"resolved_type": "Name",
					"default_value": "",
					"linked_count": 1
				},
				{
					"pin_name": "B",
					"direction": "Input",
					"category": "name",
					"subcategory": "None",
					"resolved_type": "Name",
					"default_value": "None",
					"linked_count": 0
				},
				{
					"pin_name": "ReturnValue",
					"direction": "Output",
					"category": "bool",
					"subcategory": "None",
					"resolved_type": "Boolean",
					"default_value": "",
					"linked_count": 1
				},
				{
					"pin_name": "ErrorTolerance",
					"direction": "Input",
					"category": "None",
					"subcategory": "None",
					"resolved_type": "None",
					"default_value": "",
					"linked_count": 0
				}
			],
			"target_class": "TryAutoStartPuzzleForCurrentContext"
		},
		{
			"node_id": "K2Node_IfThenElse_3",
			"node_name": "K2Node_IfThenElse_3",
			"node_kind": "Branch",
			"ue_class": "K2Node_IfThenElse",
			"title": "Branch",
			"title_single_line": "Branch",
			"comment": "",
			"guid": "d0ad896a-4de5-8d1a-e48b-eb9f02007ed3",
			"x": 1088,
			"y": 192,
			"has_error": false,
			"has_warning": false,
			"pins": [
				{
					"pin_name": "execute",
					"direction": "Input",
					"category": "exec",
					"subcategory": "None",
					"resolved_type": "exec",
					"default_value": "",
					"linked_count": 1
				},
				{
					"pin_name": "Condition",
					"direction": "Input",
					"category": "bool",
					"subcategory": "None",
					"resolved_type": "Boolean",
					"default_value": "true",
					"linked_count": 1
				},
				{
					"pin_name": "then",
					"direction": "Output",
					"category": "exec",
					"subcategory": "None",
					"resolved_type": "exec",
					"default_value": "",
					"linked_count": 1
				},
				{
					"pin_name": "else",
					"direction": "Output",
					"category": "exec",
					"subcategory": "None",
					"resolved_type": "exec",
					"default_value": "",
					"linked_count": 1
				}
			],
			"target_class": "TryAutoStartPuzzleForCurrentContext"
		},
		{
			"node_id": "K2Node_CallFunction_0",
			"node_name": "K2Node_CallFunction_0",
			"node_kind": "FunctionCall",
			"ue_class": "K2Node_CallFunction",
			"title": "Debug Info",
			"title_single_line": "Debug Info",
			"comment": "",
			"guid": "cc5c750e-420e-3be1-f76d-468a0d7d1b17",
			"x": 1536,
			"y": 304,
			"has_error": false,
			"has_warning": false,
			"pins": [
				{
					"pin_name": "execute",
					"direction": "Input",
					"category": "exec",
					"subcategory": "None",
					"resolved_type": "exec",
					"default_value": "",
					"linked_count": 1
				},
				{
					"pin_name": "then",
					"direction": "Output",
					"category": "exec",
					"subcategory": "None",
					"resolved_type": "exec",
					"default_value": "",
					"linked_count": 1
				},
				{
					"pin_name": "self",
					"direction": "Input",
					"category": "object",
					"subcategory": "None",
					"resolved_type": "BFL_Debug_C",
					"default_value": "",
					"linked_count": 0
				},
				{
					"pin_name": "WorldContextObject",
					"direction": "Input",
					"category": "object",
					"subcategory": "None",
					"resolved_type": "Object",
					"default_value": "",
					"linked_count": 1
				},
				{
					"pin_name": "Category",
					"direction": "Input",
					"category": "byte",
					"subcategory": "None",
					"resolved_type": "Byte/Enum",
					"default_value": "NewEnumerator2",
					"linked_count": 0
				},
				{
					"pin_name": "SenderName",
					"direction": "Input",
					"category": "name",
					"subcategory": "None",
					"resolved_type": "Name",
					"default_value": "None",
					"linked_count": 1
				},
				{
					"pin_name": "Message",
					"direction": "Input",
					"category": "string",
					"subcategory": "None",
					"resolved_type": "String",
					"default_value": "[PuzzleController] Auto-start skipped because CurrentGhostId is None",
					"linked_count": 0
				},
				{
					"pin_name": "__WorldContext",
					"direction": "Input",
					"category": "object",
					"subcategory": "None",
					"resolved_type": "Object",
					"default_value": "",
					"linked_count": 0
				}
			],
			"target_class": "TryAutoStartPuzzleForCurrentContext"
		},
		{
			"node_id": "K2Node_Self_0",
			"node_name": "K2Node_Self_0",
			"node_kind": "SelfReference",
			"ue_class": "K2Node_Self",
			"title": "Self-Reference",
			"title_single_line": "Self-Reference",
			"comment": "",
			"guid": "7bd561cc-4f1c-927a-b552-678ac77686cf",
			"x": 1168,
			"y": 384,
			"has_error": false,
			"has_warning": false,
			"pins": [
				{
					"pin_name": "self",
					"direction": "Output",
					"category": "object",
					"subcategory": "self",
					"resolved_type": "object",
					"default_value": "",
					"linked_count": 2
				}
			],
			"target_class": "TryAutoStartPuzzleForCurrentContext"
		},
		{
			"node_id": "K2Node_CallFunction_1",
			"node_name": "K2Node_CallFunction_1",
			"node_kind": "FunctionCall",
			"ue_class": "K2Node_CallFunction",
			"title": "Get Sender Name",
			"title_single_line": "Get Sender Name",
			"comment": "",
			"guid": "31f3be4a-4164-2850-316c-b9aeb156cd0e",
			"x": 1328,
			"y": 432,
			"has_error": false,
			"has_warning": false,
			"pins": [
				{
					"pin_name": "self",
					"direction": "Input",
					"category": "object",
					"subcategory": "None",
					"resolved_type": "BFL_Debug_C",
					"default_value": "",
					"linked_count": 0
				},
				{
					"pin_name": "Ref",
					"direction": "Input",
					"category": "object",
					"subcategory": "None",
					"resolved_type": "Object",
					"default_value": "",
					"linked_count": 1
				},
				{
					"pin_name": "__WorldContext",
					"direction": "Input",
					"category": "object",
					"subcategory": "None",
					"resolved_type": "Object",
					"default_value": "",
					"linked_count": 0
				},
				{
					"pin_name": "Name",
					"direction": "Output",
					"category": "name",
					"subcategory": "None",
					"resolved_type": "Name",
					"default_value": "None",
					"linked_count": 1
				}
			],
			"target_class": "TryAutoStartPuzzleForCurrentContext"
		},
		{
			"node_id": "K2Node_FunctionResult_5",
			"node_name": "K2Node_FunctionResult_5",
			"node_kind": "Return",
			"ue_class": "K2Node_FunctionResult",
			"title": "Return Node",
			"title_single_line": "Return Node",
			"comment": "",
			"guid": "8e43a306-4318-34bd-4cf1-53be72e56431",
			"x": 2224,
			"y": 304,
			"has_error": false,
			"has_warning": false,
			"pins": [
				{
					"pin_name": "execute",
					"direction": "Input",
					"category": "exec",
					"subcategory": "None",
					"resolved_type": "exec",
					"default_value": "",
					"linked_count": 1
				},
				{
					"pin_name": "bStartedPuzzle",
					"direction": "Input",
					"category": "bool",
					"subcategory": "None",
					"resolved_type": "Boolean",
					"default_value": "false",
					"linked_count": 0
				}
			],
			"target_class": "TryAutoStartPuzzleForCurrentContext"
		},
		{
			"node_id": "K2Node_CallFunction_6",
			"node_name": "K2Node_CallFunction_6",
			"node_kind": "FunctionCall",
			"ue_class": "K2Node_CallFunction",
			"title": "Start Next Valid Puzzle for Current Context\nTarget is BP Puzzle Controller",
			"title_single_line": "Start Next Valid Puzzle for Current Context",
			"comment": "",
			"guid": "ec8a1d01-4ddf-2553-1e7a-d7ba61776e40",
			"x": 2912,
			"y": 192,
			"has_error": true,
			"has_warning": false,
			"pins": [
				{
					"pin_name": "execute",
					"direction": "Input",
					"category": "exec",
					"subcategory": "None",
					"resolved_type": "exec",
					"default_value": "",
					"linked_count": 1
				},
				{
					"pin_name": "then",
					"direction": "Output",
					"category": "exec",
					"subcategory": "None",
					"resolved_type": "exec",
					"default_value": "",
					"linked_count": 1
				},
				{
					"pin_name": "self",
					"direction": "Input",
					"category": "object",
					"subcategory": "self",
					"resolved_type": "object",
					"default_value": "",
					"linked_count": 0
				},
				{
					"pin_name": "NewParam",
					"direction": "Output",
					"category": "bool",
					"subcategory": "None",
					"resolved_type": "Boolean",
					"default_value": "false",
					"linked_count": 0
				},
				{
					"pin_name": "bStartedPuzzle",
					"direction": "Output",
					"category": "bool",
					"subcategory": "None",
					"resolved_type": "Boolean",
					"default_value": "false",
					"linked_count": 1
				}
			],
			"target_class": "TryAutoStartPuzzleForCurrentContext"
		},
		{
			"node_id": "K2Node_FunctionResult_1",
			"node_name": "K2Node_FunctionResult_1",
			"node_kind": "Return",
			"ue_class": "K2Node_FunctionResult",
			"title": "Return Node",
			"title_single_line": "Return Node",
			"comment": "",
			"guid": "0925cc61-4792-dc3c-eaaf-3799fa50cdeb",
			"x": 3360,
			"y": 208,
			"has_error": false,
			"has_warning": false,
			"pins": [
				{
					"pin_name": "execute",
					"direction": "Input",
					"category": "exec",
					"subcategory": "None",
					"resolved_type": "exec",
					"default_value": "",
					"linked_count": 1
				},
				{
					"pin_name": "bStartedPuzzle",
					"direction": "Input",
					"category": "bool",
					"subcategory": "None",
					"resolved_type": "Boolean",
					"default_value": "false",
					"linked_count": 1
				}
			],
			"target_class": "TryAutoStartPuzzleForCurrentContext"
		}
	],
	"exec_flow": [
		{
			"from_node_id": "K2Node_FunctionEntry_0",
			"from_node_title": "TryAutoStartPuzzleForCurrentContext",
			"from_pin": "then",
			"to_node_id": "K2Node_IfThenElse_0",
			"to_node_title": "Branch",
			"to_pin": "execute"
		},
		{
			"from_node_id": "K2Node_IfThenElse_0",
			"from_node_title": "Branch",
			"from_pin": "then",
			"to_node_id": "K2Node_IfThenElse_1",
			"to_node_title": "Branch",
			"to_pin": "execute"
		},
		{
			"from_node_id": "K2Node_IfThenElse_0",
			"from_node_title": "Branch",
			"from_pin": "else",
			"to_node_id": "K2Node_FunctionResult_2",
			"to_node_title": "Return Node",
			"to_pin": "execute"
		},
		{
			"from_node_id": "K2Node_IfThenElse_1",
			"from_node_title": "Branch",
			"from_pin": "then",
			"to_node_id": "K2Node_CallFunction_2",
			"to_node_title": "Debug Info",
			"to_pin": "execute"
		},
		{
			"from_node_id": "K2Node_IfThenElse_1",
			"from_node_title": "Branch",
			"from_pin": "else",
			"to_node_id": "K2Node_IfThenElse_2",
			"to_node_title": "Branch",
			"to_pin": "execute"
		},
		{
			"from_node_id": "K2Node_CallFunction_2",
			"from_node_title": "Debug Info",
			"from_pin": "then",
			"to_node_id": "K2Node_FunctionResult_3",
			"to_node_title": "Return Node",
			"to_pin": "execute"
		},
		{
			"from_node_id": "K2Node_IfThenElse_2",
			"from_node_title": "Branch",
			"from_pin": "then",
			"to_node_id": "K2Node_Knot_0",
			"to_node_title": "Reroute Node",
			"to_pin": "InputPin"
		},
		{
			"from_node_id": "K2Node_IfThenElse_2",
			"from_node_title": "Branch",
			"from_pin": "else",
			"to_node_id": "K2Node_IfThenElse_3",
			"to_node_title": "Branch",
			"to_pin": "execute"
		},
		{
			"from_node_id": "K2Node_CallFunction_4",
			"from_node_title": "Debug Info",
			"from_pin": "then",
			"to_node_id": "K2Node_FunctionResult_4",
			"to_node_title": "Return Node",
			"to_pin": "execute"
		},
		{
			"from_node_id": "K2Node_Knot_0",
			"from_node_title": "Reroute Node",
			"from_pin": "OutputPin",
			"to_node_id": "K2Node_CallFunction_4",
			"to_node_title": "Debug Info",
			"to_pin": "execute"
		},
		{
			"from_node_id": "K2Node_IfThenElse_3",
			"from_node_title": "Branch",
			"from_pin": "then",
			"to_node_id": "K2Node_CallFunction_6",
			"to_node_title": "Start Next Valid Puzzle for Current Context\nTarget is BP Puzzle Controller",
			"to_pin": "execute"
		},
		{
			"from_node_id": "K2Node_IfThenElse_3",
			"from_node_title": "Branch",
			"from_pin": "else",
			"to_node_id": "K2Node_CallFunction_0",
			"to_node_title": "Debug Info",
			"to_pin": "execute"
		},
		{
			"from_node_id": "K2Node_CallFunction_0",
			"from_node_title": "Debug Info",
			"from_pin": "then",
			"to_node_id": "K2Node_FunctionResult_5",
			"to_node_title": "Return Node",
			"to_pin": "execute"
		},
		{
			"from_node_id": "K2Node_CallFunction_6",
			"from_node_title": "Start Next Valid Puzzle for Current Context\nTarget is BP Puzzle Controller",
			"from_pin": "then",
			"to_node_id": "K2Node_FunctionResult_1",
			"to_node_title": "Return Node",
			"to_pin": "execute"
		}
	],
	"data_links": [
		{
			"from_node_id": "K2Node_VariableGet_0",
			"from_node_title": "Get bAutoStartFirstPuzzleForCurrentGhost",
			"from_pin": "bAutoStartFirstPuzzleForCurrentGhost",
			"to_node_id": "K2Node_IfThenElse_0",
			"to_node_title": "Branch",
			"to_pin": "Condition"
		},
		{
			"from_node_id": "K2Node_VariableGet_1",
			"from_node_title": "Get bPuzzleRestoredFromSave",
			"from_pin": "bPuzzleRestoredFromSave",
			"to_node_id": "K2Node_IfThenElse_1",
			"to_node_title": "Branch",
			"to_pin": "Condition"
		},
		{
			"from_node_id": "K2Node_Self_1",
			"from_node_title": "Self-Reference",
			"from_pin": "self",
			"to_node_id": "K2Node_CallFunction_2",
			"to_node_title": "Debug Info",
			"to_pin": "WorldContextObject"
		},
		{
			"from_node_id": "K2Node_Self_1",
			"from_node_title": "Self-Reference",
			"from_pin": "self",
			"to_node_id": "K2Node_CallFunction_3",
			"to_node_title": "Get Sender Name",
			"to_pin": "Ref"
		},
		{
			"from_node_id": "K2Node_CallFunction_3",
			"from_node_title": "Get Sender Name",
			"from_pin": "Name",
			"to_node_id": "K2Node_CallFunction_2",
			"to_node_title": "Debug Info",
			"to_pin": "SenderName"
		},
		{
			"from_node_id": "K2Node_VariableGet_2",
			"from_node_title": "Get bHasActivePuzzle",
			"from_pin": "bHasActivePuzzle",
			"to_node_id": "K2Node_IfThenElse_2",
			"to_node_title": "Branch",
			"to_pin": "Condition"
		},
		{
			"from_node_id": "K2Node_Self_2",
			"from_node_title": "Self-Reference",
			"from_pin": "self",
			"to_node_id": "K2Node_CallFunction_4",
			"to_node_title": "Debug Info",
			"to_pin": "WorldContextObject"
		},
		{
			"from_node_id": "K2Node_Self_2",
			"from_node_title": "Self-Reference",
			"from_pin": "self",
			"to_node_id": "K2Node_CallFunction_5",
			"to_node_title": "Get Sender Name",
			"to_pin": "Ref"
		},
		{
			"from_node_id": "K2Node_CallFunction_5",
			"from_node_title": "Get Sender Name",
			"from_pin": "Name",
			"to_node_id": "K2Node_CallFunction_4",
			"to_node_title": "Debug Info",
			"to_pin": "SenderName"
		},
		{
			"from_node_id": "K2Node_VariableGet_3",
			"from_node_title": "Get CurrentGhostId",
			"from_pin": "CurrentGhostId",
			"to_node_id": "K2Node_PromotableOperator_0",
			"to_node_title": "Not Equal (Name)",
			"to_pin": "A"
		},
		{
			"from_node_id": "K2Node_PromotableOperator_0",
			"from_node_title": "Not Equal (Name)",
			"from_pin": "ReturnValue",
			"to_node_id": "K2Node_IfThenElse_3",
			"to_node_title": "Branch",
			"to_pin": "Condition"
		},
		{
			"from_node_id": "K2Node_Self_0",
			"from_node_title": "Self-Reference",
			"from_pin": "self",
			"to_node_id": "K2Node_CallFunction_0",
			"to_node_title": "Debug Info",
			"to_pin": "WorldContextObject"
		},
		{
			"from_node_id": "K2Node_Self_0",
			"from_node_title": "Self-Reference",
			"from_pin": "self",
			"to_node_id": "K2Node_CallFunction_1",
			"to_node_title": "Get Sender Name",
			"to_pin": "Ref"
		},
		{
			"from_node_id": "K2Node_CallFunction_1",
			"from_node_title": "Get Sender Name",
			"from_pin": "Name",
			"to_node_id": "K2Node_CallFunction_0",
			"to_node_title": "Debug Info",
			"to_pin": "SenderName"
		},
		{
			"from_node_id": "K2Node_CallFunction_6",
			"from_node_title": "Start Next Valid Puzzle for Current Context\nTarget is BP Puzzle Controller",
			"from_pin": "bStartedPuzzle",
			"to_node_id": "K2Node_FunctionResult_1",
			"to_node_title": "Return Node",
			"to_pin": "bStartedPuzzle"
		}
	],
	"problems": []
}